MANIFEST.in
setup.py
src/fsqio.pants.contrib.buildgen.python.egg-info/PKG-INFO
src/fsqio.pants.contrib.buildgen.python.egg-info/SOURCES.txt
src/fsqio.pants.contrib.buildgen.python.egg-info/dependency_links.txt
src/fsqio.pants.contrib.buildgen.python.egg-info/entry_points.txt
src/fsqio.pants.contrib.buildgen.python.egg-info/namespace_packages.txt
src/fsqio.pants.contrib.buildgen.python.egg-info/requires.txt
src/fsqio.pants.contrib.buildgen.python.egg-info/top_level.txt
src/fsqio.pants.contrib.buildgen.python.egg-info/zip-safe
src/pants/__init__.py
src/pants/contrib/__init__.py
src/pants/contrib/buildgen/__init__.py
src/pants/contrib/buildgen/python/__init__.py
src/pants/contrib/buildgen/python/buildgen_python.py
src/pants/contrib/buildgen/python/map_python_exported_symbols.py
src/pants/contrib/buildgen/python/python_import_parser.py
src/pants/contrib/buildgen/python/register.py
src/pants/contrib/buildgen/python/third_party_map_python.py